{"games":[{"Date":"Sun Jan 03 22:42:04 GMT 2021","WhiteNic":"xtgn","WhitePoint":"1475","BlackNic":"zdfhb","BlackPoint":"556"},{"Date":"Sun Jan 03 22:32:27 GMT 2021","WhiteNic":"zdfgh","WhitePoint":"1227","BlackNic":"xrtjrj","BlackPoint":"112"},{"Date":"Sun Jan 03 22:20:18 GMT 2021","WhiteNic":"fxgmj","WhitePoint":"1136","BlackNic":"fhcjmc","BlackPoint":"424"},{"Date":"Sun Jan 03 22:09:15 GMT 2021","WhiteNic":"serth","WhitePoint":"1787","BlackNic":"fctyk","BlackPoint":"874"},{"Date":"Sun Jan 03 17:41:36 GMT 2021","WhiteNic":"okk","WhitePoint":"11","BlackNic":"okkk","BlackPoint":"333"},{"Date":"Sun Jan 03 17:41:36 GMT 2021","WhiteNic":"first","WhitePoint":"11","BlackNic":"sec","BlackPoint":"333"},{"Date":"Sun Jan 03 22:49:56 GMT 2021","WhiteNic":"rgd","WhitePoint":"1764","BlackNic":"gr","BlackPoint":"631"}]}